perhaps/__init__.py
perhaps/client.py
perhaps/core/__init__.py
perhaps/core/api_error.py
perhaps/core/datetime_utils.py
perhaps/core/jsonable_encoder.py
perhaps/core/remove_none_from_headers.py
perhaps/py.typed
perhaps_api-0.0.8.dist-info/METADATA
perhaps_api-0.0.8.dist-info/WHEEL
perhaps_api-0.0.8.dist-info/RECORD
